qubit_simulator/__init__.py
qubit_simulator/gates.py
qubit_simulator/simulator.py
qubit_simulator-0.1.0.dist-info/LICENSE
qubit_simulator-0.1.0.dist-info/METADATA
qubit_simulator-0.1.0.dist-info/WHEEL
qubit_simulator-0.1.0.dist-info/top_level.txt
qubit_simulator-0.1.0.dist-info/RECORD
