Metadata-Version: 2.2
Name: qubit-simulator
Version: 0.1.0
Summary: A simple qubit simulator
Author: Spencer Churchill
Author-email: churchill@ionq.com
Classifier: Development Status :: 5 - Production/Stable
Classifier: Intended Audience :: Science/Research
Classifier: License :: OSI Approved :: MIT License
Classifier: Programming Language :: Python :: 3
License-File: LICENSE
Requires-Dist: numpy
Provides-Extra: visualization
Requires-Dist: matplotlib; extra == "visualization"
Dynamic: author
Dynamic: author-email
Dynamic: classifier
Dynamic: description
Dynamic: description-content-type
Dynamic: provides-extra
Dynamic: requires-dist
Dynamic: summary
